[
    {
        "id": 1,
        "title": "Ambrosia Gulab Jamun",
        "image": [
            "assets/images/shop/21.jpg",
            "assets/images/shop/5.jpg",
            "assets/images/shop/6.jpg",
            "assets/images/shop/7.jpg",
            "assets/images/shop/9.jpg"
        ],
        "price": 150,
        "discount": 20,
        "sale": true,
        "category": [
            1,
            2
        ],
        "tags": [
            1,
            2
        ],
        "rating": 4,
        "postdate":"10th April 2021",
        "stock": true,
        "featured": true,
        "trending": false,
        "sku": "006-bhg",
        "shorttext": "Honey has the ability to absorb moisture directly from the air, a phenomenon called hygroscopy. The amount of water the honey absorbs is dependent on the relative humidity of the air. Because honey contains yeast, this hygroscopic nature requires that honey be stored in sealed containers to prevent fermentation, which usually.",
        "htmltext": "<p>Individual honeys from different plant sources contain over 100 volatile organic compounds , which play a primary role in determining honey flavors and aromas are carbon-based compounds that readily vaporize into the air, providing aroma, including the scents of flowers, essential oils, or ripening fruit The typical chemical families of VOCs found in honey include.</p>",
        "reviews": [
            {
                "user":[1],
                "commentdate":"15th April, 2021",
                "comment":"Honey is a sweet, viscous food substance made by honey bees and some related insects eiusmod tempor incididunt ut labore et dolore magna aliqua. Ut enim ad minim veniam, quis nostrud exercitation ullamco laboris nisi ut aliquip ex ea commodo consequat."
            },
            {
                "user":[2],
                "commentdate":"14th April, 2021",
                "comment":"Honey is a sweet, viscous food substance made by honey bees and some related insects eiusmod tempor incididunt ut labore et dolore magna aliqua. Ut enim ad minim veniam, quis nostrud exercitation ullamco laboris nisi ut aliquip ex ea commodo consequat."
            }
        ],
        "additionalinfo":[
            {
                "title":"Color",
                "text":"Red, White, Black"
            },
            {
                "title":"Material",
                "text":"Steel, Wood, Stone"
            },
            {
                "title":"Weight",
                "text":"400 Gram"
            }
        ]
    },
    {
        "id": 2,
        "title": "Millers Gulab Jamun",
        "image": [
            "assets/images/shop/5.jpg",
            "assets/images/shop/6.jpg",
            "assets/images/shop/7.jpg",
            "assets/images/shop/9.jpg",
            "assets/images/shop/10.jpg"
        ],
        "price": 200,
        "discount": "",
        "sale": true,
        "category": [
            3,
            4
        ],
        "tags": [
            3,
            4
        ],
        "rating": 4,
        "postdate":"10th April 2021",
        "stock": false,
        "featured": false,
        "trending": false,
        "sku": "006-bhg",
        "shorttext": "Honey has the ability to absorb moisture directly from the air, a phenomenon called hygroscopy. The amount of water the honey absorbs is dependent on the relative humidity of the air. Because honey contains yeast, this hygroscopic nature requires that honey be stored in sealed containers to prevent fermentation, which usually.",
        "htmltext": "<p>Individual honeys from different plant sources contain over 100 volatile organic compounds , which play a primary role in determining honey flavors and aromas are carbon-based compounds that readily vaporize into the air, providing aroma, including the scents of flowers, essential oils, or ripening fruit The typical chemical families of VOCs found in honey include.</p>",
        "reviews": [
            {
                "user":[1],
                "commentdate":"15th April, 2021",
                "comment":"Honey is a sweet, viscous food substance made by honey bees and some related insects eiusmod tempor incididunt ut labore et dolore magna aliqua. Ut enim ad minim veniam, quis nostrud exercitation ullamco laboris nisi ut aliquip ex ea commodo consequat."
            },
            {
                "user":[2],
                "commentdate":"14th April, 2021",
                "comment":"Honey is a sweet, viscous food substance made by honey bees and some related insects eiusmod tempor incididunt ut labore et dolore magna aliqua. Ut enim ad minim veniam, quis nostrud exercitation ullamco laboris nisi ut aliquip ex ea commodo consequat."
            }
        ],
        "additionalinfo":[
            {
                "title":"Color",
                "text":"Red, White, Black"
            },
            {
                "title":"Material",
                "text":"Steel, Wood, Stone"
            },
            {
                "title":"Weight",
                "text":"400 Gram"
            }
        ]
    },
    {
        "id": 3,
        "title": "Natural Gulab jamun",
        "image": [
            "assets/images/shop/6.jpg",
            "assets/images/shop/7.jpg",
            "assets/images/shop/9.jpg",
            "assets/images/shop/10.jpg",
            "assets/images/shop/11.jpg"
        ],
        "price": 120,
        "discount": 20,
        "sale": false,
        "category": [
            5,
            6
        ],
        "tags": [
            5,
            6
        ],
        "rating": 4,
        "postdate":"10th April 2021",
        "stock": true,
        "featured": true,
        "trending": true,
        "sku": "006-bhg",
        "shorttext": "Honey has the ability to absorb moisture directly from the air, a phenomenon called hygroscopy. The amount of water the honey absorbs is dependent on the relative humidity of the air. Because honey contains yeast, this hygroscopic nature requires that honey be stored in sealed containers to prevent fermentation, which usually.",
        "htmltext": "<p>Individual honeys from different plant sources contain over 100 volatile organic compounds , which play a primary role in determining honey flavors and aromas are carbon-based compounds that readily vaporize into the air, providing aroma, including the scents of flowers, essential oils, or ripening fruit The typical chemical families of VOCs found in honey include.</p>",
        "reviews": [
            {
                "user":[1],
                "commentdate":"15th April, 2021",
                "comment":"Honey is a sweet, viscous food substance made by honey bees and some related insects eiusmod tempor incididunt ut labore et dolore magna aliqua. Ut enim ad minim veniam, quis nostrud exercitation ullamco laboris nisi ut aliquip ex ea commodo consequat."
            },
            {
                "user":[2],
                "commentdate":"14th April, 2021",
                "comment":"Honey is a sweet, viscous food substance made by honey bees and some related insects eiusmod tempor incididunt ut labore et dolore magna aliqua. Ut enim ad minim veniam, quis nostrud exercitation ullamco laboris nisi ut aliquip ex ea commodo consequat."
            }
        ],
        "additionalinfo":[
            {
                "title":"Color",
                "text":"Red, White, Black"
            },
            {
                "title":"Material",
                "text":"Steel, Wood, Stone"
            },
            {
                "title":"Weight",
                "text":"400 Gram"
            }
        ]
    },
    {
        "id": 4,
        "title": "Virginia Gulab jamun",
        "image": [
            "assets/images/shop/7.jpg",
            "assets/images/shop/9.jpg",
            "assets/images/shop/10.jpg",
            "assets/images/shop/11.jpg",
            "assets/images/shop/12.jpg"
        ],
        "price": 150,
        "discount": "",
        "sale": false,
        "category": [
            1,
            2
        ],
        "tags": [
            1,
            2
        ],
        "rating": 4,
        "postdate":"10th April 2021",
        "stock": true,
        "featured": true,
        "trending": false,
        "sku": "006-bhg",
        "shorttext": "Honey has the ability to absorb moisture directly from the air, a phenomenon called hygroscopy. The amount of water the honey absorbs is dependent on the relative humidity of the air. Because honey contains yeast, this hygroscopic nature requires that honey be stored in sealed containers to prevent fermentation, which usually.",
        "htmltext": "<p>Individual honeys from different plant sources contain over 100 volatile organic compounds , which play a primary role in determining honey flavors and aromas are carbon-based compounds that readily vaporize into the air, providing aroma, including the scents of flowers, essential oils, or ripening fruit The typical chemical families of VOCs found in honey include.</p>",
        "reviews": [
            {
                "user":[1],
                "commentdate":"15th April, 2021",
                "comment":"Honey is a sweet, viscous food substance made by honey bees and some related insects eiusmod tempor incididunt ut labore et dolore magna aliqua. Ut enim ad minim veniam, quis nostrud exercitation ullamco laboris nisi ut aliquip ex ea commodo consequat."
            },
            {
                "user":[2],
                "commentdate":"14th April, 2021",
                "comment":"Honey is a sweet, viscous food substance made by honey bees and some related insects eiusmod tempor incididunt ut labore et dolore magna aliqua. Ut enim ad minim veniam, quis nostrud exercitation ullamco laboris nisi ut aliquip ex ea commodo consequat."
            }
        ],
        "additionalinfo":[
            {
                "title":"Color",
                "text":"Red, White, Black"
            },
            {
                "title":"Material",
                "text":"Steel, Wood, Stone"
            },
            {
                "title":"Weight",
                "text":"400 Gram"
            }
        ]
    },
    {
        "id": 5,
        "title": "Organic Gulab Jamun",
        "image": [
            "assets/images/shop/9.jpg",
            "assets/images/shop/10.jpg",
            "assets/images/shop/11.jpg",
            "assets/images/shop/12.jpg",
            "assets/images/shop/13.jpg"
        ],
        "price": 300,
        "discount": "",
        "sale": true,
        "category": [
            3,
            4
        ],
        "tags": [
            3,
            4
        ],
        "rating": 4,
        "postdate":"10th April 2021",
        "stock": false,
        "featured": false,
        "trending": false,
        "sku": "006-bhg",
        "shorttext": "Honey has the ability to absorb moisture directly from the air, a phenomenon called hygroscopy. The amount of water the honey absorbs is dependent on the relative humidity of the air. Because honey contains yeast, this hygroscopic nature requires that honey be stored in sealed containers to prevent fermentation, which usually.",
        "htmltext": "<p>Individual honeys from different plant sources contain over 100 volatile organic compounds , which play a primary role in determining honey flavors and aromas are carbon-based compounds that readily vaporize into the air, providing aroma, including the scents of flowers, essential oils, or ripening fruit The typical chemical families of VOCs found in honey include.</p>",
        "reviews": [
            {
                "user":[1],
                "commentdate":"15th April, 2021",
                "comment":"Honey is a sweet, viscous food substance made by honey bees and some related insects eiusmod tempor incididunt ut labore et dolore magna aliqua. Ut enim ad minim veniam, quis nostrud exercitation ullamco laboris nisi ut aliquip ex ea commodo consequat."
            },
            {
                "user":[2],
                "commentdate":"14th April, 2021",
                "comment":"Honey is a sweet, viscous food substance made by honey bees and some related insects eiusmod tempor incididunt ut labore et dolore magna aliqua. Ut enim ad minim veniam, quis nostrud exercitation ullamco laboris nisi ut aliquip ex ea commodo consequat."
            }
        ],
        "additionalinfo":[
            {
                "title":"Color",
                "text":"Red, White, Black"
            },
            {
                "title":"Material",
                "text":"Steel, Wood, Stone"
            },
            {
                "title":"Weight",
                "text":"400 Gram"
            }
        ]
    },
    {
        "id": 6,
        "title": "Raw Honey",
        "image": [
            "assets/images/shop/10.jpg",
            "assets/images/shop/11.jpg",
            "assets/images/shop/12.jpg",
            "assets/images/shop/13.jpg",
            "assets/images/shop/14.jpg"
        ],
        "price": 200,
        "discount": "",
        "sale": false,
        "category": [
            5,
            6
        ],
        "tags": [
            5,
            6
        ],
        "rating": 4,
        "postdate":"10th April 2021",
        "stock": true,
        "featured": true,
        "trending": true,
        "sku": "006-bhg",
        "shorttext": "Honey has the ability to absorb moisture directly from the air, a phenomenon called hygroscopy. The amount of water the honey absorbs is dependent on the relative humidity of the air. Because honey contains yeast, this hygroscopic nature requires that honey be stored in sealed containers to prevent fermentation, which usually.",
        "htmltext": "<p>Individual honeys from different plant sources contain over 100 volatile organic compounds , which play a primary role in determining honey flavors and aromas are carbon-based compounds that readily vaporize into the air, providing aroma, including the scents of flowers, essential oils, or ripening fruit The typical chemical families of VOCs found in honey include.</p>",
        "reviews": [
            {
                "user":[1],
                "commentdate":"15th April, 2021",
                "comment":"Honey is a sweet, viscous food substance made by honey bees and some related insects eiusmod tempor incididunt ut labore et dolore magna aliqua. Ut enim ad minim veniam, quis nostrud exercitation ullamco laboris nisi ut aliquip ex ea commodo consequat."
            },
            {
                "user":[2],
                "commentdate":"14th April, 2021",
                "comment":"Honey is a sweet, viscous food substance made by honey bees and some related insects eiusmod tempor incididunt ut labore et dolore magna aliqua. Ut enim ad minim veniam, quis nostrud exercitation ullamco laboris nisi ut aliquip ex ea commodo consequat."
            }
        ],
        "additionalinfo":[
            {
                "title":"Color",
                "text":"Red, White, Black"
            },
            {
                "title":"Material",
                "text":"Steel, Wood, Stone"
            },
            {
                "title":"Weight",
                "text":"400 Gram"
            }
        ]
    },
    {
        "id": 7,
        "title": "Gulab Jamun harvest",
        "image": [
            "assets/images/shop/11.jpg",
            "assets/images/shop/12.jpg",
            "assets/images/shop/13.jpg",
            "assets/images/shop/14.jpg",
            "assets/images/shop/15.jpg"
        ],
        "price": 100,
        "discount": 25,
        "sale": false,
        "category": [
            1,
            2
        ],
        "tags": [
            1,
            2
        ],
        "rating": 4,
        "postdate":"10th April 2021",
        "stock": true,
        "featured": true,
        "trending": false,
        "sku": "006-bhg",
        "shorttext": "Honey has the ability to absorb moisture directly from the air, a phenomenon called hygroscopy. The amount of water the honey absorbs is dependent on the relative humidity of the air. Because honey contains yeast, this hygroscopic nature requires that honey be stored in sealed containers to prevent fermentation, which usually.",
        "htmltext": "<p>Individual honeys from different plant sources contain over 100 volatile organic compounds , which play a primary role in determining honey flavors and aromas are carbon-based compounds that readily vaporize into the air, providing aroma, including the scents of flowers, essential oils, or ripening fruit The typical chemical families of VOCs found in honey include.</p>",
        "reviews": [
            {
                "user":[1],
                "commentdate":"15th April, 2021",
                "comment":"Honey is a sweet, viscous food substance made by honey bees and some related insects eiusmod tempor incididunt ut labore et dolore magna aliqua. Ut enim ad minim veniam, quis nostrud exercitation ullamco laboris nisi ut aliquip ex ea commodo consequat."
            },
            {
                "user":[2],
                "commentdate":"14th April, 2021",
                "comment":"Honey is a sweet, viscous food substance made by honey bees and some related insects eiusmod tempor incididunt ut labore et dolore magna aliqua. Ut enim ad minim veniam, quis nostrud exercitation ullamco laboris nisi ut aliquip ex ea commodo consequat."
            }
        ],
        "additionalinfo":[
            {
                "title":"Color",
                "text":"Red, White, Black"
            },
            {
                "title":"Material",
                "text":"Steel, Wood, Stone"
            },
            {
                "title":"Weight",
                "text":"400 Gram"
            }
        ]
    },
    {
        "id": 8,
        "title": "Creamed Gulab jamun",
        "image": [
            "assets/images/shop/12.jpg",
            "assets/images/shop/13.jpg",
            "assets/images/shop/14.jpg",
            "assets/images/shop/15.jpg",
            "assets/images/shop/16.jpg"
        ],
        "price": 300,
        "discount": "",
        "sale": false,
        "category": [
            3,
            4
        ],
        "tags": [
            3,
            4
        ],
        "rating": 4,
        "postdate":"10th April 2021",
        "stock": true,
        "featured": true,
        "trending": true,
        "sku": "006-bhg",
        "shorttext": "Honey has the ability to absorb moisture directly from the air, a phenomenon called hygroscopy. The amount of water the honey absorbs is dependent on the relative humidity of the air. Because honey contains yeast, this hygroscopic nature requires that honey be stored in sealed containers to prevent fermentation, which usually.",
        "htmltext": "<p>Individual honeys from different plant sources contain over 100 volatile organic compounds , which play a primary role in determining honey flavors and aromas are carbon-based compounds that readily vaporize into the air, providing aroma, including the scents of flowers, essential oils, or ripening fruit The typical chemical families of VOCs found in honey include.</p>",
        "reviews": [
            {
                "user":[1],
                "commentdate":"15th April, 2021",
                "comment":"Honey is a sweet, viscous food substance made by honey bees and some related insects eiusmod tempor incididunt ut labore et dolore magna aliqua. Ut enim ad minim veniam, quis nostrud exercitation ullamco laboris nisi ut aliquip ex ea commodo consequat."
            },
            {
                "user":[2],
                "commentdate":"14th April, 2021",
                "comment":"Honey is a sweet, viscous food substance made by honey bees and some related insects eiusmod tempor incididunt ut labore et dolore magna aliqua. Ut enim ad minim veniam, quis nostrud exercitation ullamco laboris nisi ut aliquip ex ea commodo consequat."
            }
        ],
        "additionalinfo":[
            {
                "title":"Color",
                "text":"Red, White, Black"
            },
            {
                "title":"Material",
                "text":"Steel, Wood, Stone"
            },
            {
                "title":"Weight",
                "text":"400 Gram"
            }
        ]
    },
    {
        "id": 9,
        "title": "Infused Gulab Jamun",
        "image": [
            "assets/images/shop/13.jpg",
            "assets/images/shop/14.jpg",
            "assets/images/shop/15.jpg",
            "assets/images/shop/16.jpg",
            "assets/images/shop/17.jpg"
        ],
        "price": 300,
        "discount": "",
        "sale": true,
        "category": [
            5,
            6
        ],
        "tags": [
            5,
            6
        ],
        "rating": 4,
        "postdate":"10th April 2021",
        "stock": true,
        "featured": false,
        "trending": false,
        "sku": "006-bhg",
        "shorttext": "Honey has the ability to absorb moisture directly from the air, a phenomenon called hygroscopy. The amount of water the honey absorbs is dependent on the relative humidity of the air. Because honey contains yeast, this hygroscopic nature requires that honey be stored in sealed containers to prevent fermentation, which usually.",
        "htmltext": "<p>Individual honeys from different plant sources contain over 100 volatile organic compounds , which play a primary role in determining honey flavors and aromas are carbon-based compounds that readily vaporize into the air, providing aroma, including the scents of flowers, essential oils, or ripening fruit The typical chemical families of VOCs found in honey include.</p>",
        "reviews": [
            {
                "user":[1],
                "commentdate":"15th April, 2021",
                "comment":"Honey is a sweet, viscous food substance made by honey bees and some related insects eiusmod tempor incididunt ut labore et dolore magna aliqua. Ut enim ad minim veniam, quis nostrud exercitation ullamco laboris nisi ut aliquip ex ea commodo consequat."
            },
            {
                "user":[2],
                "commentdate":"14th April, 2021",
                "comment":"Honey is a sweet, viscous food substance made by honey bees and some related insects eiusmod tempor incididunt ut labore et dolore magna aliqua. Ut enim ad minim veniam, quis nostrud exercitation ullamco laboris nisi ut aliquip ex ea commodo consequat."
            }
        ],
        "additionalinfo":[
            {
                "title":"Color",
                "text":"Red, White, Black"
            },
            {
                "title":"Material",
                "text":"Steel, Wood, Stone"
            },
            {
                "title":"Weight",
                "text":"400 Gram"
            }
        ]
    },
    {
        "id": 10,
        "title": "Gulab Jamun Products",
        "image": [
            "assets/images/shop/14.jpg",
            "assets/images/shop/15.jpg",
            "assets/images/shop/16.jpg",
            "assets/images/shop/17.jpg",
            "assets/images/shop/18.jpg"
        ],
        "price": 90,
        "discount": 15,
        "sale": true,
        "category": [
            1,
            2
        ],
        "tags": [
            1,
            2
        ],
        "rating": 4,
        "postdate":"10th April 2021",
        "stock": true,
        "featured": true,
        "trending": false,
        "sku": "006-bhg",
        "shorttext": "Honey has the ability to absorb moisture directly from the air, a phenomenon called hygroscopy. The amount of water the honey absorbs is dependent on the relative humidity of the air. Because honey contains yeast, this hygroscopic nature requires that honey be stored in sealed containers to prevent fermentation, which usually.",
        "htmltext": "<p>Individual honeys from different plant sources contain over 100 volatile organic compounds , which play a primary role in determining honey flavors and aromas are carbon-based compounds that readily vaporize into the air, providing aroma, including the scents of flowers, essential oils, or ripening fruit The typical chemical families of VOCs found in honey include.</p>",
        "reviews": [
            {
                "user":[1],
                "commentdate":"15th April, 2021",
                "comment":"Honey is a sweet, viscous food substance made by honey bees and some related insects eiusmod tempor incididunt ut labore et dolore magna aliqua. Ut enim ad minim veniam, quis nostrud exercitation ullamco laboris nisi ut aliquip ex ea commodo consequat."
            },
            {
                "user":[2],
                "commentdate":"14th April, 2021",
                "comment":"Honey is a sweet, viscous food substance made by honey bees and some related insects eiusmod tempor incididunt ut labore et dolore magna aliqua. Ut enim ad minim veniam, quis nostrud exercitation ullamco laboris nisi ut aliquip ex ea commodo consequat."
            }
        ],
        "additionalinfo":[
            {
                "title":"Color",
                "text":"Red, White, Black"
            },
            {
                "title":"Material",
                "text":"Steel, Wood, Stone"
            },
            {
                "title":"Weight",
                "text":"400 Gram"
            }
        ]
    },
    {
        "id": 11,
        "title": "100% Natural Gulab Jamun",
        "image": [
            "assets/images/shop/15.jpg",
            "assets/images/shop/16.jpg",
            "assets/images/shop/17.jpg",
            "assets/images/shop/18.jpg",
            "assets/images/shop/19.jpg"
        ],
        "price": 160,
        "discount": "",
        "sale": false,
        "category": [
            3,
            4
        ],
        "tags": [
            3,
            4
        ],
        "rating": 4,
        "postdate":"10th April 2021",
        "stock": true,
        "featured": true,
        "trending": true,
        "sku": "006-bhg",
        "shorttext": "Honey has the ability to absorb moisture directly from the air, a phenomenon called hygroscopy. The amount of water the honey absorbs is dependent on the relative humidity of the air. Because honey contains yeast, this hygroscopic nature requires that honey be stored in sealed containers to prevent fermentation, which usually.",
        "htmltext": "<p>Individual honeys from different plant sources contain over 100 volatile organic compounds , which play a primary role in determining honey flavors and aromas are carbon-based compounds that readily vaporize into the air, providing aroma, including the scents of flowers, essential oils, or ripening fruit The typical chemical families of VOCs found in honey include.</p>",
        "reviews": [
            {
                "user":[1],
                "commentdate":"15th April, 2021",
                "comment":"Honey is a sweet, viscous food substance made by honey bees and some related insects eiusmod tempor incididunt ut labore et dolore magna aliqua. Ut enim ad minim veniam, quis nostrud exercitation ullamco laboris nisi ut aliquip ex ea commodo consequat."
            },
            {
                "user":[2],
                "commentdate":"14th April, 2021",
                "comment":"Honey is a sweet, viscous food substance made by honey bees and some related insects eiusmod tempor incididunt ut labore et dolore magna aliqua. Ut enim ad minim veniam, quis nostrud exercitation ullamco laboris nisi ut aliquip ex ea commodo consequat."
            }
        ],
        "additionalinfo":[
            {
                "title":"Color",
                "text":"Red, White, Black"
            },
            {
                "title":"Material",
                "text":"Steel, Wood, Stone"
            },
            {
                "title":"Weight",
                "text":"400 Gram"
            }
        ]
    },
    {
        "id": 12,
        "title": "Tasty Gulab Jamun",
        "image": [
            "assets/images/shop/16.jpg",
            "assets/images/shop/17.jpg",
            "assets/images/shop/18.jpg",
            "assets/images/shop/19.jpg",
            "assets/images/shop/20.jpg"
        ],
        "price": 400,
        "discount": "",
        "sale": false,
        "category": [
            5,
            6
        ],
        "tags": [
            5,
            6
        ],
        "rating": 4,
        "postdate":"10th April 2021",
        "stock": true,
        "featured": false,
        "trending": false,
        "sku": "006-bhg",
        "shorttext": "Honey has the ability to absorb moisture directly from the air, a phenomenon called hygroscopy. The amount of water the honey absorbs is dependent on the relative humidity of the air. Because honey contains yeast, this hygroscopic nature requires that honey be stored in sealed containers to prevent fermentation, which usually.",
        "htmltext": "<p>Individual honeys from different plant sources contain over 100 volatile organic compounds , which play a primary role in determining honey flavors and aromas are carbon-based compounds that readily vaporize into the air, providing aroma, including the scents of flowers, essential oils, or ripening fruit The typical chemical families of VOCs found in honey include.</p>",
        "reviews": [
            {
                "user":[1],
                "commentdate":"15th April, 2021",
                "comment":"Honey is a sweet, viscous food substance made by honey bees and some related insects eiusmod tempor incididunt ut labore et dolore magna aliqua. Ut enim ad minim veniam, quis nostrud exercitation ullamco laboris nisi ut aliquip ex ea commodo consequat."
            },
            {
                "user":[2],
                "commentdate":"14th April, 2021",
                "comment":"Honey is a sweet, viscous food substance made by honey bees and some related insects eiusmod tempor incididunt ut labore et dolore magna aliqua. Ut enim ad minim veniam, quis nostrud exercitation ullamco laboris nisi ut aliquip ex ea commodo consequat."
            }
        ],
        "additionalinfo":[
            {
                "title":"Color",
                "text":"Red, White, Black"
            },
            {
                "title":"Material",
                "text":"Steel, Wood, Stone"
            },
            {
                "title":"Weight",
                "text":"400 Gram"
            }
        ]
    }
]